{
  "lastUpdated": "2026-07-13T23:15:10.126Z",
  "champion": null,
  "teams": {
    "Mexico": {
      "status": "out",
      "reached": "r16",
      "group": "A",
      "rank": 1,
      "played": 3,
      "won": 3,
      "draw": 0,
      "lost": 0,
      "gf": 6,
      "ga": 0,
      "gd": 6,
      "points": 9
    },
    "South Africa": {
      "status": "out",
      "reached": "r32",
      "group": "A",
      "rank": 2,
      "played": 3,
      "won": 1,
      "draw": 1,
      "lost": 1,
      "gf": 2,
      "ga": 3,
      "gd": -1,
      "points": 4
    },
    "South Korea": {
      "status": "out",
      "reached": "group",
      "group": "A",
      "rank": 3,
      "played": 3,
      "won": 1,
      "draw": 0,
      "lost": 2,
      "gf": 2,
      "ga": 3,
      "gd": -1,
      "points": 3
    },
    "Czechia": {
      "status": "out",
      "reached": "group",
      "group": "A",
      "rank": 4,
      "played": 3,
      "won": 0,
      "draw": 1,
      "lost": 2,
      "gf": 2,
      "ga": 6,
      "gd": -4,
      "points": 1
    },
    "Switzerland": {
      "status": "out",
      "reached": "qf",
      "group": "B",
      "rank": 1,
      "played": 3,
      "won": 2,
      "draw": 1,
      "lost": 0,
      "gf": 7,
      "ga": 3,
      "gd": 4,
      "points": 7
    },
    "Canada": {
      "status": "out",
      "reached": "r16",
      "group": "B",
      "rank": 2,
      "played": 3,
      "won": 1,
      "draw": 1,
      "lost": 1,
      "gf": 8,
      "ga": 3,
      "gd": 5,
      "points": 4
    },
    "Bosnia": {
      "status": "out",
      "reached": "r32",
      "group": "B",
      "rank": 3,
      "played": 3,
      "won": 1,
      "draw": 1,
      "lost": 1,
      "gf": 5,
      "ga": 6,
      "gd": -1,
      "points": 4
    },
    "Qatar": {
      "status": "out",
      "reached": "group",
      "group": "B",
      "rank": 4,
      "played": 3,
      "won": 0,
      "draw": 1,
      "lost": 2,
      "gf": 2,
      "ga": 10,
      "gd": -8,
      "points": 1
    },
    "Brazil": {
      "status": "out",
      "reached": "r16",
      "group": "C",
      "rank": 1,
      "played": 3,
      "won": 2,
      "draw": 1,
      "lost": 0,
      "gf": 7,
      "ga": 1,
      "gd": 6,
      "points": 7
    },
    "Morocco": {
      "status": "out",
      "reached": "qf",
      "group": "C",
      "rank": 2,
      "played": 3,
      "won": 2,
      "draw": 1,
      "lost": 0,
      "gf": 6,
      "ga": 3,
      "gd": 3,
      "points": 7
    },
    "Scotland": {
      "status": "out",
      "reached": "group",
      "group": "C",
      "rank": 3,
      "played": 3,
      "won": 1,
      "draw": 0,
      "lost": 2,
      "gf": 1,
      "ga": 4,
      "gd": -3,
      "points": 3
    },
    "Haiti": {
      "status": "out",
      "reached": "group",
      "group": "C",
      "rank": 4,
      "played": 3,
      "won": 0,
      "draw": 0,
      "lost": 3,
      "gf": 2,
      "ga": 8,
      "gd": -6,
      "points": 0
    },
    "USA": {
      "status": "out",
      "reached": "r16",
      "group": "D",
      "rank": 1,
      "played": 3,
      "won": 2,
      "draw": 0,
      "lost": 1,
      "gf": 8,
      "ga": 4,
      "gd": 4,
      "points": 6
    },
    "Australia": {
      "status": "out",
      "reached": "r32",
      "group": "D",
      "rank": 2,
      "played": 3,
      "won": 1,
      "draw": 1,
      "lost": 1,
      "gf": 2,
      "ga": 2,
      "gd": 0,
      "points": 4
    },
    "Paraguay": {
      "status": "out",
      "reached": "r16",
      "group": "D",
      "rank": 3,
      "played": 3,
      "won": 1,
      "draw": 1,
      "lost": 1,
      "gf": 2,
      "ga": 4,
      "gd": -2,
      "points": 4
    },
    "Türkiye": {
      "status": "out",
      "reached": "group",
      "group": "D",
      "rank": 4,
      "played": 3,
      "won": 1,
      "draw": 0,
      "lost": 2,
      "gf": 3,
      "ga": 5,
      "gd": -2,
      "points": 3
    },
    "Germany": {
      "status": "out",
      "reached": "r32",
      "group": "E",
      "rank": 1,
      "played": 3,
      "won": 2,
      "draw": 0,
      "lost": 1,
      "gf": 10,
      "ga": 4,
      "gd": 6,
      "points": 6
    },
    "Ivory Coast": {
      "status": "out",
      "reached": "r32",
      "group": "E",
      "rank": 2,
      "played": 3,
      "won": 2,
      "draw": 0,
      "lost": 1,
      "gf": 4,
      "ga": 2,
      "gd": 2,
      "points": 6
    },
    "Ecuador": {
      "status": "out",
      "reached": "r32",
      "group": "E",
      "rank": 3,
      "played": 3,
      "won": 1,
      "draw": 1,
      "lost": 1,
      "gf": 2,
      "ga": 2,
      "gd": 0,
      "points": 4
    },
    "Curaçao": {
      "status": "out",
      "reached": "group",
      "group": "E",
      "rank": 4,
      "played": 3,
      "won": 0,
      "draw": 1,
      "lost": 2,
      "gf": 1,
      "ga": 9,
      "gd": -8,
      "points": 1
    },
    "Netherlands": {
      "status": "out",
      "reached": "r32",
      "group": "F",
      "rank": 1,
      "played": 3,
      "won": 2,
      "draw": 1,
      "lost": 0,
      "gf": 10,
      "ga": 4,
      "gd": 6,
      "points": 7
    },
    "Japan": {
      "status": "out",
      "reached": "r32",
      "group": "F",
      "rank": 2,
      "played": 3,
      "won": 1,
      "draw": 2,
      "lost": 0,
      "gf": 7,
      "ga": 3,
      "gd": 4,
      "points": 5
    },
    "Sweden": {
      "status": "out",
      "reached": "r32",
      "group": "F",
      "rank": 3,
      "played": 3,
      "won": 1,
      "draw": 1,
      "lost": 1,
      "gf": 7,
      "ga": 7,
      "gd": 0,
      "points": 4
    },
    "Tunisia": {
      "status": "out",
      "reached": "group",
      "group": "F",
      "rank": 4,
      "played": 3,
      "won": 0,
      "draw": 0,
      "lost": 3,
      "gf": 2,
      "ga": 12,
      "gd": -10,
      "points": 0
    },
    "Belgium": {
      "status": "out",
      "reached": "qf",
      "group": "G",
      "rank": 1,
      "played": 3,
      "won": 1,
      "draw": 2,
      "lost": 0,
      "gf": 6,
      "ga": 2,
      "gd": 4,
      "points": 5
    },
    "Egypt": {
      "status": "out",
      "reached": "r16",
      "group": "G",
      "rank": 2,
      "played": 3,
      "won": 1,
      "draw": 2,
      "lost": 0,
      "gf": 5,
      "ga": 3,
      "gd": 2,
      "points": 5
    },
    "Iran": {
      "status": "out",
      "reached": "group",
      "group": "G",
      "rank": 3,
      "played": 3,
      "won": 0,
      "draw": 3,
      "lost": 0,
      "gf": 3,
      "ga": 3,
      "gd": 0,
      "points": 3
    },
    "New Zealand": {
      "status": "out",
      "reached": "group",
      "group": "G",
      "rank": 4,
      "played": 3,
      "won": 0,
      "draw": 1,
      "lost": 2,
      "gf": 4,
      "ga": 10,
      "gd": -6,
      "points": 1
    },
    "Spain": {
      "status": "alive",
      "reached": "sf",
      "group": "H",
      "rank": 1,
      "played": 3,
      "won": 2,
      "draw": 1,
      "lost": 0,
      "gf": 5,
      "ga": 0,
      "gd": 5,
      "points": 7
    },
    "Cape Verde": {
      "status": "out",
      "reached": "r32",
      "group": "H",
      "rank": 2,
      "played": 3,
      "won": 0,
      "draw": 3,
      "lost": 0,
      "gf": 2,
      "ga": 2,
      "gd": 0,
      "points": 3
    },
    "Uruguay": {
      "status": "out",
      "reached": "group",
      "group": "H",
      "rank": 3,
      "played": 3,
      "won": 0,
      "draw": 2,
      "lost": 1,
      "gf": 3,
      "ga": 4,
      "gd": -1,
      "points": 2
    },
    "Saudi Arabia": {
      "status": "out",
      "reached": "group",
      "group": "H",
      "rank": 4,
      "played": 3,
      "won": 0,
      "draw": 2,
      "lost": 1,
      "gf": 1,
      "ga": 5,
      "gd": -4,
      "points": 2
    },
    "France": {
      "status": "alive",
      "reached": "sf",
      "group": "I",
      "rank": 1,
      "played": 3,
      "won": 3,
      "draw": 0,
      "lost": 0,
      "gf": 10,
      "ga": 2,
      "gd": 8,
      "points": 9
    },
    "Norway": {
      "status": "out",
      "reached": "qf",
      "group": "I",
      "rank": 2,
      "played": 3,
      "won": 2,
      "draw": 0,
      "lost": 1,
      "gf": 8,
      "ga": 7,
      "gd": 1,
      "points": 6
    },
    "Senegal": {
      "status": "out",
      "reached": "r32",
      "group": "I",
      "rank": 3,
      "played": 3,
      "won": 1,
      "draw": 0,
      "lost": 2,
      "gf": 8,
      "ga": 6,
      "gd": 2,
      "points": 3
    },
    "Iraq": {
      "status": "out",
      "reached": "group",
      "group": "I",
      "rank": 4,
      "played": 3,
      "won": 0,
      "draw": 0,
      "lost": 3,
      "gf": 1,
      "ga": 12,
      "gd": -11,
      "points": 0
    },
    "Argentina": {
      "status": "alive",
      "reached": "sf",
      "group": "J",
      "rank": 1,
      "played": 3,
      "won": 3,
      "draw": 0,
      "lost": 0,
      "gf": 8,
      "ga": 1,
      "gd": 7,
      "points": 9
    },
    "Austria": {
      "status": "out",
      "reached": "r32",
      "group": "J",
      "rank": 2,
      "played": 3,
      "won": 1,
      "draw": 1,
      "lost": 1,
      "gf": 6,
      "ga": 6,
      "gd": 0,
      "points": 4
    },
    "Algeria": {
      "status": "out",
      "reached": "r32",
      "group": "J",
      "rank": 3,
      "played": 3,
      "won": 1,
      "draw": 1,
      "lost": 1,
      "gf": 5,
      "ga": 7,
      "gd": -2,
      "points": 4
    },
    "Jordan": {
      "status": "out",
      "reached": "group",
      "group": "J",
      "rank": 4,
      "played": 3,
      "won": 0,
      "draw": 0,
      "lost": 3,
      "gf": 3,
      "ga": 8,
      "gd": -5,
      "points": 0
    },
    "Colombia": {
      "status": "out",
      "reached": "r16",
      "group": "K",
      "rank": 1,
      "played": 3,
      "won": 2,
      "draw": 1,
      "lost": 0,
      "gf": 4,
      "ga": 1,
      "gd": 3,
      "points": 7
    },
    "Portugal": {
      "status": "out",
      "reached": "r16",
      "group": "K",
      "rank": 2,
      "played": 3,
      "won": 1,
      "draw": 2,
      "lost": 0,
      "gf": 6,
      "ga": 1,
      "gd": 5,
      "points": 5
    },
    "DR Congo": {
      "status": "out",
      "reached": "r32",
      "group": "K",
      "rank": 3,
      "played": 3,
      "won": 1,
      "draw": 1,
      "lost": 1,
      "gf": 4,
      "ga": 3,
      "gd": 1,
      "points": 4
    },
    "Uzbekistan": {
      "status": "out",
      "reached": "group",
      "group": "K",
      "rank": 4,
      "played": 3,
      "won": 0,
      "draw": 0,
      "lost": 3,
      "gf": 2,
      "ga": 11,
      "gd": -9,
      "points": 0
    },
    "England": {
      "status": "alive",
      "reached": "sf",
      "group": "L",
      "rank": 1,
      "played": 3,
      "won": 2,
      "draw": 1,
      "lost": 0,
      "gf": 6,
      "ga": 2,
      "gd": 4,
      "points": 7
    },
    "Croatia": {
      "status": "out",
      "reached": "r32",
      "group": "L",
      "rank": 2,
      "played": 3,
      "won": 2,
      "draw": 0,
      "lost": 1,
      "gf": 5,
      "ga": 5,
      "gd": 0,
      "points": 6
    },
    "Ghana": {
      "status": "out",
      "reached": "r32",
      "group": "L",
      "rank": 3,
      "played": 3,
      "won": 1,
      "draw": 1,
      "lost": 1,
      "gf": 2,
      "ga": 2,
      "gd": 0,
      "points": 4
    },
    "Panama": {
      "status": "out",
      "reached": "group",
      "group": "L",
      "rank": 4,
      "played": 3,
      "won": 0,
      "draw": 0,
      "lost": 3,
      "gf": 0,
      "ga": 4,
      "gd": -4,
      "points": 0
    }
  },
  "fixtures": [
    {
      "date": "2026-06-11T19:00:00Z",
      "stage": "group",
      "group": "A",
      "home": "Mexico",
      "away": "South Africa",
      "hs": 2,
      "as": 0,
      "status": "FINISHED"
    },
    {
      "date": "2026-06-12T02:00:00Z",
      "stage": "group",
      "group": "A",
      "home": "South Korea",
      "away": "Czechia",
      "hs": 2,
      "as": 1,
      "status": "FINISHED"
    },
    {
      "date": "2026-06-12T19:00:00Z",
      "stage": "group",
      "group": "B",
      "home": "Canada",
      "away": "Bosnia",
      "hs": 1,
      "as": 1,
      "status": "FINISHED"
    },
    {
      "date": "2026-06-13T01:00:00Z",
      "stage": "group",
      "group": "D",
      "home": "USA",
      "away": "Paraguay",
      "hs": 4,
      "as": 1,
      "status": "FINISHED"
    },
    {
      "date": "2026-06-13T19:00:00Z",
      "stage": "group",
      "group": "B",
      "home": "Qatar",
      "away": "Switzerland",
      "hs": 1,
      "as": 1,
      "status": "FINISHED"
    },
    {
      "date": "2026-06-13T22:00:00Z",
      "stage": "group",
      "group": "C",
      "home": "Brazil",
      "away": "Morocco",
      "hs": 1,
      "as": 1,
      "status": "FINISHED"
    },
    {
      "date": "2026-06-14T01:00:00Z",
      "stage": "group",
      "group": "C",
      "home": "Haiti",
      "away": "Scotland",
      "hs": 0,
      "as": 1,
      "status": "FINISHED"
    },
    {
      "date": "2026-06-14T04:00:00Z",
      "stage": "group",
      "group": "D",
      "home": "Australia",
      "away": "Türkiye",
      "hs": 2,
      "as": 0,
      "status": "FINISHED"
    },
    {
      "date": "2026-06-14T17:00:00Z",
      "stage": "group",
      "group": "E",
      "home": "Germany",
      "away": "Curaçao",
      "hs": 7,
      "as": 1,
      "status": "FINISHED"
    },
    {
      "date": "2026-06-14T20:00:00Z",
      "stage": "group",
      "group": "F",
      "home": "Netherlands",
      "away": "Japan",
      "hs": 2,
      "as": 2,
      "status": "FINISHED"
    },
    {
      "date": "2026-06-14T23:00:00Z",
      "stage": "group",
      "group": "E",
      "home": "Ivory Coast",
      "away": "Ecuador",
      "hs": 1,
      "as": 0,
      "status": "FINISHED"
    },
    {
      "date": "2026-06-15T02:00:00Z",
      "stage": "group",
      "group": "F",
      "home": "Sweden",
      "away": "Tunisia",
      "hs": 5,
      "as": 1,
      "status": "FINISHED"
    },
    {
      "date": "2026-06-15T16:00:00Z",
      "stage": "group",
      "group": "H",
      "home": "Spain",
      "away": "Cape Verde",
      "hs": 0,
      "as": 0,
      "status": "FINISHED"
    },
    {
      "date": "2026-06-15T19:00:00Z",
      "stage": "group",
      "group": "G",
      "home": "Belgium",
      "away": "Egypt",
      "hs": 1,
      "as": 1,
      "status": "FINISHED"
    },
    {
      "date": "2026-06-15T22:00:00Z",
      "stage": "group",
      "group": "H",
      "home": "Saudi Arabia",
      "away": "Uruguay",
      "hs": 1,
      "as": 1,
      "status": "FINISHED"
    },
    {
      "date": "2026-06-16T01:00:00Z",
      "stage": "group",
      "group": "G",
      "home": "Iran",
      "away": "New Zealand",
      "hs": 2,
      "as": 2,
      "status": "FINISHED"
    },
    {
      "date": "2026-06-16T19:00:00Z",
      "stage": "group",
      "group": "I",
      "home": "France",
      "away": "Senegal",
      "hs": 3,
      "as": 1,
      "status": "FINISHED"
    },
    {
      "date": "2026-06-16T22:00:00Z",
      "stage": "group",
      "group": "I",
      "home": "Iraq",
      "away": "Norway",
      "hs": 1,
      "as": 4,
      "status": "FINISHED"
    },
    {
      "date": "2026-06-17T01:00:00Z",
      "stage": "group",
      "group": "J",
      "home": "Argentina",
      "away": "Algeria",
      "hs": 3,
      "as": 0,
      "status": "FINISHED"
    },
    {
      "date": "2026-06-17T04:00:00Z",
      "stage": "group",
      "group": "J",
      "home": "Austria",
      "away": "Jordan",
      "hs": 3,
      "as": 1,
      "status": "FINISHED"
    },
    {
      "date": "2026-06-17T17:00:00Z",
      "stage": "group",
      "group": "K",
      "home": "Portugal",
      "away": "DR Congo",
      "hs": 1,
      "as": 1,
      "status": "FINISHED"
    },
    {
      "date": "2026-06-17T20:00:00Z",
      "stage": "group",
      "group": "L",
      "home": "England",
      "away": "Croatia",
      "hs": 4,
      "as": 2,
      "status": "FINISHED"
    },
    {
      "date": "2026-06-17T23:00:00Z",
      "stage": "group",
      "group": "L",
      "home": "Ghana",
      "away": "Panama",
      "hs": 1,
      "as": 0,
      "status": "FINISHED"
    },
    {
      "date": "2026-06-18T02:00:00Z",
      "stage": "group",
      "group": "K",
      "home": "Uzbekistan",
      "away": "Colombia",
      "hs": 1,
      "as": 3,
      "status": "FINISHED"
    },
    {
      "date": "2026-06-18T16:00:00Z",
      "stage": "group",
      "group": "A",
      "home": "Czechia",
      "away": "South Africa",
      "hs": 1,
      "as": 1,
      "status": "FINISHED"
    },
    {
      "date": "2026-06-18T19:00:00Z",
      "stage": "group",
      "group": "B",
      "home": "Switzerland",
      "away": "Bosnia",
      "hs": 4,
      "as": 1,
      "status": "FINISHED"
    },
    {
      "date": "2026-06-18T22:00:00Z",
      "stage": "group",
      "group": "B",
      "home": "Canada",
      "away": "Qatar",
      "hs": 6,
      "as": 0,
      "status": "FINISHED"
    },
    {
      "date": "2026-06-19T01:00:00Z",
      "stage": "group",
      "group": "A",
      "home": "Mexico",
      "away": "South Korea",
      "hs": 1,
      "as": 0,
      "status": "FINISHED"
    },
    {
      "date": "2026-06-19T19:00:00Z",
      "stage": "group",
      "group": "D",
      "home": "USA",
      "away": "Australia",
      "hs": 2,
      "as": 0,
      "status": "FINISHED"
    },
    {
      "date": "2026-06-19T22:00:00Z",
      "stage": "group",
      "group": "C",
      "home": "Scotland",
      "away": "Morocco",
      "hs": 0,
      "as": 1,
      "status": "FINISHED"
    },
    {
      "date": "2026-06-20T00:30:00Z",
      "stage": "group",
      "group": "C",
      "home": "Brazil",
      "away": "Haiti",
      "hs": 3,
      "as": 0,
      "status": "FINISHED"
    },
    {
      "date": "2026-06-20T03:00:00Z",
      "stage": "group",
      "group": "D",
      "home": "Türkiye",
      "away": "Paraguay",
      "hs": 0,
      "as": 1,
      "status": "FINISHED"
    },
    {
      "date": "2026-06-20T17:00:00Z",
      "stage": "group",
      "group": "F",
      "home": "Netherlands",
      "away": "Sweden",
      "hs": 5,
      "as": 1,
      "status": "FINISHED"
    },
    {
      "date": "2026-06-20T20:00:00Z",
      "stage": "group",
      "group": "E",
      "home": "Germany",
      "away": "Ivory Coast",
      "hs": 2,
      "as": 1,
      "status": "FINISHED"
    },
    {
      "date": "2026-06-21T00:00:00Z",
      "stage": "group",
      "group": "E",
      "home": "Ecuador",
      "away": "Curaçao",
      "hs": 0,
      "as": 0,
      "status": "FINISHED"
    },
    {
      "date": "2026-06-21T04:00:00Z",
      "stage": "group",
      "group": "F",
      "home": "Tunisia",
      "away": "Japan",
      "hs": 0,
      "as": 4,
      "status": "FINISHED"
    },
    {
      "date": "2026-06-21T16:00:00Z",
      "stage": "group",
      "group": "H",
      "home": "Spain",
      "away": "Saudi Arabia",
      "hs": 4,
      "as": 0,
      "status": "FINISHED"
    },
    {
      "date": "2026-06-21T19:00:00Z",
      "stage": "group",
      "group": "G",
      "home": "Belgium",
      "away": "Iran",
      "hs": 0,
      "as": 0,
      "status": "FINISHED"
    },
    {
      "date": "2026-06-21T22:00:00Z",
      "stage": "group",
      "group": "H",
      "home": "Uruguay",
      "away": "Cape Verde",
      "hs": 2,
      "as": 2,
      "status": "FINISHED"
    },
    {
      "date": "2026-06-22T01:00:00Z",
      "stage": "group",
      "group": "G",
      "home": "New Zealand",
      "away": "Egypt",
      "hs": 1,
      "as": 3,
      "status": "FINISHED"
    },
    {
      "date": "2026-06-22T17:00:00Z",
      "stage": "group",
      "group": "J",
      "home": "Argentina",
      "away": "Austria",
      "hs": 2,
      "as": 0,
      "status": "FINISHED"
    },
    {
      "date": "2026-06-22T21:00:00Z",
      "stage": "group",
      "group": "I",
      "home": "France",
      "away": "Iraq",
      "hs": 3,
      "as": 0,
      "status": "FINISHED"
    },
    {
      "date": "2026-06-23T00:00:00Z",
      "stage": "group",
      "group": "I",
      "home": "Norway",
      "away": "Senegal",
      "hs": 3,
      "as": 2,
      "status": "FINISHED"
    },
    {
      "date": "2026-06-23T03:00:00Z",
      "stage": "group",
      "group": "J",
      "home": "Jordan",
      "away": "Algeria",
      "hs": 1,
      "as": 2,
      "status": "FINISHED"
    },
    {
      "date": "2026-06-23T17:00:00Z",
      "stage": "group",
      "group": "K",
      "home": "Portugal",
      "away": "Uzbekistan",
      "hs": 5,
      "as": 0,
      "status": "FINISHED"
    },
    {
      "date": "2026-06-23T20:00:00Z",
      "stage": "group",
      "group": "L",
      "home": "England",
      "away": "Ghana",
      "hs": 0,
      "as": 0,
      "status": "FINISHED"
    },
    {
      "date": "2026-06-23T23:00:00Z",
      "stage": "group",
      "group": "L",
      "home": "Panama",
      "away": "Croatia",
      "hs": 0,
      "as": 1,
      "status": "FINISHED"
    },
    {
      "date": "2026-06-24T02:00:00Z",
      "stage": "group",
      "group": "K",
      "home": "Colombia",
      "away": "DR Congo",
      "hs": 1,
      "as": 0,
      "status": "FINISHED"
    },
    {
      "date": "2026-06-24T19:00:00Z",
      "stage": "group",
      "group": "B",
      "home": "Switzerland",
      "away": "Canada",
      "hs": 2,
      "as": 1,
      "status": "FINISHED"
    },
    {
      "date": "2026-06-24T19:00:00Z",
      "stage": "group",
      "group": "B",
      "home": "Bosnia",
      "away": "Qatar",
      "hs": 3,
      "as": 1,
      "status": "FINISHED"
    },
    {
      "date": "2026-06-24T22:00:00Z",
      "stage": "group",
      "group": "C",
      "home": "Morocco",
      "away": "Haiti",
      "hs": 4,
      "as": 2,
      "status": "FINISHED"
    },
    {
      "date": "2026-06-24T22:00:00Z",
      "stage": "group",
      "group": "C",
      "home": "Scotland",
      "away": "Brazil",
      "hs": 0,
      "as": 3,
      "status": "FINISHED"
    },
    {
      "date": "2026-06-25T01:00:00Z",
      "stage": "group",
      "group": "A",
      "home": "Czechia",
      "away": "Mexico",
      "hs": 0,
      "as": 3,
      "status": "FINISHED"
    },
    {
      "date": "2026-06-25T01:00:00Z",
      "stage": "group",
      "group": "A",
      "home": "South Africa",
      "away": "South Korea",
      "hs": 1,
      "as": 0,
      "status": "FINISHED"
    },
    {
      "date": "2026-06-25T20:00:00Z",
      "stage": "group",
      "group": "E",
      "home": "Ecuador",
      "away": "Germany",
      "hs": 2,
      "as": 1,
      "status": "FINISHED"
    },
    {
      "date": "2026-06-25T20:00:00Z",
      "stage": "group",
      "group": "E",
      "home": "Curaçao",
      "away": "Ivory Coast",
      "hs": 0,
      "as": 2,
      "status": "FINISHED"
    },
    {
      "date": "2026-06-25T23:00:00Z",
      "stage": "group",
      "group": "F",
      "home": "Tunisia",
      "away": "Netherlands",
      "hs": 1,
      "as": 3,
      "status": "FINISHED"
    },
    {
      "date": "2026-06-25T23:00:00Z",
      "stage": "group",
      "group": "F",
      "home": "Japan",
      "away": "Sweden",
      "hs": 1,
      "as": 1,
      "status": "FINISHED"
    },
    {
      "date": "2026-06-26T02:00:00Z",
      "stage": "group",
      "group": "D",
      "home": "Türkiye",
      "away": "USA",
      "hs": 3,
      "as": 2,
      "status": "FINISHED"
    },
    {
      "date": "2026-06-26T02:00:00Z",
      "stage": "group",
      "group": "D",
      "home": "Paraguay",
      "away": "Australia",
      "hs": 0,
      "as": 0,
      "status": "FINISHED"
    },
    {
      "date": "2026-06-26T19:00:00Z",
      "stage": "group",
      "group": "I",
      "home": "Norway",
      "away": "France",
      "hs": 1,
      "as": 4,
      "status": "FINISHED"
    },
    {
      "date": "2026-06-26T19:00:00Z",
      "stage": "group",
      "group": "I",
      "home": "Senegal",
      "away": "Iraq",
      "hs": 5,
      "as": 0,
      "status": "FINISHED"
    },
    {
      "date": "2026-06-27T00:00:00Z",
      "stage": "group",
      "group": "H",
      "home": "Uruguay",
      "away": "Spain",
      "hs": 0,
      "as": 1,
      "status": "FINISHED"
    },
    {
      "date": "2026-06-27T00:00:00Z",
      "stage": "group",
      "group": "H",
      "home": "Cape Verde",
      "away": "Saudi Arabia",
      "hs": 0,
      "as": 0,
      "status": "FINISHED"
    },
    {
      "date": "2026-06-27T03:00:00Z",
      "stage": "group",
      "group": "G",
      "home": "New Zealand",
      "away": "Belgium",
      "hs": 1,
      "as": 5,
      "status": "FINISHED"
    },
    {
      "date": "2026-06-27T03:00:00Z",
      "stage": "group",
      "group": "G",
      "home": "Egypt",
      "away": "Iran",
      "hs": 1,
      "as": 1,
      "status": "FINISHED"
    },
    {
      "date": "2026-06-27T21:00:00Z",
      "stage": "group",
      "group": "L",
      "home": "Panama",
      "away": "England",
      "hs": 0,
      "as": 2,
      "status": "FINISHED"
    },
    {
      "date": "2026-06-27T21:00:00Z",
      "stage": "group",
      "group": "L",
      "home": "Croatia",
      "away": "Ghana",
      "hs": 2,
      "as": 1,
      "status": "FINISHED"
    },
    {
      "date": "2026-06-27T23:30:00Z",
      "stage": "group",
      "group": "K",
      "home": "Colombia",
      "away": "Portugal",
      "hs": 0,
      "as": 0,
      "status": "FINISHED"
    },
    {
      "date": "2026-06-27T23:30:00Z",
      "stage": "group",
      "group": "K",
      "home": "DR Congo",
      "away": "Uzbekistan",
      "hs": 3,
      "as": 1,
      "status": "FINISHED"
    },
    {
      "date": "2026-06-28T02:00:00Z",
      "stage": "group",
      "group": "J",
      "home": "Jordan",
      "away": "Argentina",
      "hs": 1,
      "as": 3,
      "status": "FINISHED"
    },
    {
      "date": "2026-06-28T02:00:00Z",
      "stage": "group",
      "group": "J",
      "home": "Algeria",
      "away": "Austria",
      "hs": 3,
      "as": 3,
      "status": "FINISHED"
    },
    {
      "date": "2026-06-28T19:00:00Z",
      "stage": "r32",
      "group": null,
      "home": "South Africa",
      "away": "Canada",
      "hs": 0,
      "as": 1,
      "status": "FINISHED"
    },
    {
      "date": "2026-06-29T17:00:00Z",
      "stage": "r32",
      "group": null,
      "home": "Brazil",
      "away": "Japan",
      "hs": 2,
      "as": 1,
      "status": "FINISHED"
    },
    {
      "date": "2026-06-29T20:30:00Z",
      "stage": "r32",
      "group": null,
      "home": "Germany",
      "away": "Paraguay",
      "hs": 4,
      "as": 5,
      "status": "FINISHED"
    },
    {
      "date": "2026-06-30T01:00:00Z",
      "stage": "r32",
      "group": null,
      "home": "Netherlands",
      "away": "Morocco",
      "hs": 3,
      "as": 4,
      "status": "FINISHED"
    },
    {
      "date": "2026-06-30T17:00:00Z",
      "stage": "r32",
      "group": null,
      "home": "Ivory Coast",
      "away": "Norway",
      "hs": 1,
      "as": 2,
      "status": "FINISHED"
    },
    {
      "date": "2026-06-30T21:00:00Z",
      "stage": "r32",
      "group": null,
      "home": "France",
      "away": "Sweden",
      "hs": 3,
      "as": 0,
      "status": "FINISHED"
    },
    {
      "date": "2026-07-01T02:00:00Z",
      "stage": "r32",
      "group": null,
      "home": "Mexico",
      "away": "Ecuador",
      "hs": 2,
      "as": 0,
      "status": "FINISHED"
    },
    {
      "date": "2026-07-01T16:00:00Z",
      "stage": "r32",
      "group": null,
      "home": "England",
      "away": "DR Congo",
      "hs": 2,
      "as": 1,
      "status": "FINISHED"
    },
    {
      "date": "2026-07-01T20:00:00Z",
      "stage": "r32",
      "group": null,
      "home": "Belgium",
      "away": "Senegal",
      "hs": 3,
      "as": 2,
      "status": "FINISHED"
    },
    {
      "date": "2026-07-02T00:00:00Z",
      "stage": "r32",
      "group": null,
      "home": "USA",
      "away": "Bosnia",
      "hs": 2,
      "as": 0,
      "status": "FINISHED"
    },
    {
      "date": "2026-07-02T19:00:00Z",
      "stage": "r32",
      "group": null,
      "home": "Spain",
      "away": "Austria",
      "hs": 3,
      "as": 0,
      "status": "FINISHED"
    },
    {
      "date": "2026-07-02T23:00:00Z",
      "stage": "r32",
      "group": null,
      "home": "Portugal",
      "away": "Croatia",
      "hs": 2,
      "as": 1,
      "status": "FINISHED"
    },
    {
      "date": "2026-07-03T03:00:00Z",
      "stage": "r32",
      "group": null,
      "home": "Switzerland",
      "away": "Algeria",
      "hs": 2,
      "as": 0,
      "status": "FINISHED"
    },
    {
      "date": "2026-07-03T18:00:00Z",
      "stage": "r32",
      "group": null,
      "home": "Australia",
      "away": "Egypt",
      "hs": 3,
      "as": 5,
      "status": "FINISHED"
    },
    {
      "date": "2026-07-03T22:00:00Z",
      "stage": "r32",
      "group": null,
      "home": "Argentina",
      "away": "Cape Verde",
      "hs": 3,
      "as": 2,
      "status": "FINISHED"
    },
    {
      "date": "2026-07-04T01:30:00Z",
      "stage": "r32",
      "group": null,
      "home": "Colombia",
      "away": "Ghana",
      "hs": 1,
      "as": 0,
      "status": "FINISHED"
    },
    {
      "date": "2026-07-04T17:00:00Z",
      "stage": "r16",
      "group": null,
      "home": "Canada",
      "away": "Morocco",
      "hs": 0,
      "as": 3,
      "status": "FINISHED"
    },
    {
      "date": "2026-07-04T21:00:00Z",
      "stage": "r16",
      "group": null,
      "home": "Paraguay",
      "away": "France",
      "hs": 0,
      "as": 1,
      "status": "FINISHED"
    },
    {
      "date": "2026-07-05T20:00:00Z",
      "stage": "r16",
      "group": null,
      "home": "Brazil",
      "away": "Norway",
      "hs": 1,
      "as": 2,
      "status": "FINISHED"
    },
    {
      "date": "2026-07-06T01:00:00Z",
      "stage": "r16",
      "group": null,
      "home": "Mexico",
      "away": "England",
      "hs": 2,
      "as": 3,
      "status": "FINISHED"
    },
    {
      "date": "2026-07-06T19:00:00Z",
      "stage": "r16",
      "group": null,
      "home": "Portugal",
      "away": "Spain",
      "hs": 0,
      "as": 1,
      "status": "FINISHED"
    },
    {
      "date": "2026-07-07T00:00:00Z",
      "stage": "r16",
      "group": null,
      "home": "USA",
      "away": "Belgium",
      "hs": 1,
      "as": 4,
      "status": "FINISHED"
    },
    {
      "date": "2026-07-07T16:00:00Z",
      "stage": "r16",
      "group": null,
      "home": "Argentina",
      "away": "Egypt",
      "hs": 3,
      "as": 2,
      "status": "FINISHED"
    },
    {
      "date": "2026-07-07T20:00:00Z",
      "stage": "r16",
      "group": null,
      "home": "Switzerland",
      "away": "Colombia",
      "hs": 4,
      "as": 3,
      "status": "FINISHED"
    },
    {
      "date": "2026-07-09T20:00:00Z",
      "stage": "qf",
      "group": null,
      "home": "France",
      "away": "Morocco",
      "hs": 2,
      "as": 0,
      "status": "FINISHED"
    },
    {
      "date": "2026-07-10T19:00:00Z",
      "stage": "qf",
      "group": null,
      "home": "Spain",
      "away": "Belgium",
      "hs": 2,
      "as": 1,
      "status": "FINISHED"
    },
    {
      "date": "2026-07-11T21:00:00Z",
      "stage": "qf",
      "group": null,
      "home": "Norway",
      "away": "England",
      "hs": 1,
      "as": 2,
      "status": "FINISHED"
    },
    {
      "date": "2026-07-12T01:00:00Z",
      "stage": "qf",
      "group": null,
      "home": "Argentina",
      "away": "Switzerland",
      "hs": 3,
      "as": 1,
      "status": "FINISHED"
    },
    {
      "date": "2026-07-14T19:00:00Z",
      "stage": "sf",
      "group": null,
      "home": "France",
      "away": "Spain",
      "hs": null,
      "as": null,
      "status": "TIMED"
    },
    {
      "date": "2026-07-15T19:00:00Z",
      "stage": "sf",
      "group": null,
      "home": "England",
      "away": "Argentina",
      "hs": null,
      "as": null,
      "status": "TIMED"
    },
    {
      "date": "2026-07-18T21:00:00Z",
      "stage": "third",
      "group": null,
      "home": "TBD",
      "away": "TBD",
      "hs": null,
      "as": null,
      "status": "TIMED"
    },
    {
      "date": "2026-07-19T19:00:00Z",
      "stage": "final",
      "group": null,
      "home": "TBD",
      "away": "TBD",
      "hs": null,
      "as": null,
      "status": "TIMED"
    }
  ]
}